cfglib/__init__.py
cfglib/config.py
cfglib/sources/__init__.py
cfglib/sources/args.py
cfglib/sources/env.py
cfglib/spec.py
cfglib/validation.py
cfglib-1.1.0.dist-info/LICENSE
cfglib-1.1.0.dist-info/WHEEL
cfglib-1.1.0.dist-info/METADATA
cfglib-1.1.0.dist-info/RECORD
