Metadata-Version: 2.1
Name: cfglib
Version: 1.1.0
Summary: An extensible configuration library
Home-page: https://github.com/swarmer/cfglib-py
License: MIT
Keywords: configuration,settings
Author: Anton Barkovsky
Author-email: anton@swarmer.me
Requires-Python: >=3.7,<4
Classifier: License :: OSI Approved :: MIT License
Classifier: Programming Language :: Python :: 3
Classifier: Programming Language :: Python :: 3.7
Classifier: Programming Language :: Python :: 3.8
Provides-Extra: docs
Requires-Dist: Sphinx (>=1.8,<2.0); extra == "docs"
Requires-Dist: sphinxcontrib-apidoc (>=0.3.0,<0.4.0); extra == "docs"
Requires-Dist: sphinxcontrib-fulltoc (>=1.2,<2.0); extra == "docs"
Project-URL: Documentation, https://cfglib.readthedocs.io/en/latest/
